wivi_graph_client_py/__init__.py
wivi_graph_client_py/client.py
wivi_graph_client_py/configuration.py
wivi_graph_client_py/device_connection.py
wivi_graph_client_py/device_info.py
wivi_graph_client_py/device_status.py
wivi_graph_client_py/device_version.py
wivi_graph_client_py/dtc.py
wivi_graph_client_py/ecu.py
wivi_graph_client_py/fail_processing.py
wivi_graph_client_py/formula.py
wivi_graph_client_py/gps.py
wivi_graph_client_py/main.py
wivi_graph_client_py/message.py
wivi_graph_client_py/network.py
wivi_graph_client_py/network_stats.py
wivi_graph_client_py/signal.py
wivi_graph_client_py/test.py
wivi_graph_client_py/version.py
wivi_graph_client_py-3.1.5.dist-info/METADATA
wivi_graph_client_py-3.1.5.dist-info/WHEEL
wivi_graph_client_py-3.1.5.dist-info/top_level.txt
wivi_graph_client_py-3.1.5.dist-info/RECORD
