Metadata-Version: 2.1
Name: wivi-graph-client-py
Version: 3.1.5
Summary: UNKNOWN
Home-page: UNKNOWN
Author: Haseeb Saif Ullah
Author-email: hsaif@intrepidcs.com
License: UNKNOWN
Platform: UNKNOWN
Classifier: Programming Language :: Python :: 3
Classifier: License :: OSI Approved :: MIT License
Classifier: Operating System :: OS Independent
Requires-Dist: graphql-core
Requires-Dist: requests
